Klassifier/VERSION
Klassifier/__init__.py
Klassifier/pipeline.py
Klassifier/predict.py
Klassifier/train_pipeline.py
Klassifier/config/__init__.py
Klassifier/config/config.py
Klassifier/config/logging_config.py
Klassifier/datasets/test.csv
Klassifier/datasets/train.csv
Klassifier/processing/__init__.py
Klassifier/processing/data_management.py
Klassifier/processing/preprocessing.py
Klassifier/processing/validation.py
Klassifier/trained_models/knn_classification_output_v.pkl
Klassifier-1.0.0.dist-info/METADATA
Klassifier-1.0.0.dist-info/WHEEL
Klassifier-1.0.0.dist-info/top_level.txt
Klassifier-1.0.0.dist-info/RECORD
